{
  "seasonLength": {
    "springLength": 51840000,
    "summerLength": 51840000,
    "fallLength": 51840000,
    "winterLength": 51840000
  },
  "seasonLock": {
    "isSeasonLocked": false,
    "lockedSeason": "WINTER"
  },
  "dimensionAllowlist": [
    "minecraft:overworld"
  ],
  "doTemperatureChanges": true,
  "shouldSnowyBiomesMeltInSummer": true,
  "shouldIceNearWaterMelt": true,
  "biomeDenylist": [
    "terralith:glacial_chasm"
  ],
  "isSeasonTiedWithSystemTime": false,
  "isInNorthHemisphere": true,
  "isSeasonMessingCrops": true,
  "isSeasonMessingBonemeal": false,
  "doCropsGrowsNormallyUnderground": true,
  "doAnimalsBreedInWinter": true,
  "notifyCompat": false,
  "debugCommandEnabled": false
}